ipyreactplayer/__init__.py
ipyreactplayer/_version.py
ipyreactplayer/player.py
ipyreactplayer/player.tsx
ipyreactplayer-0.0.2.data/data/share/jupyter/voila/templates/ipyreactplayer/static/popout.html
ipyreactplayer-0.0.2.data/data/share/jupyter/voila/templates/ipyreactplayer/static/popout.js
ipyreactplayer-0.0.2.dist-info/LICENSE
ipyreactplayer-0.0.2.dist-info/METADATA
ipyreactplayer-0.0.2.dist-info/WHEEL
ipyreactplayer-0.0.2.dist-info/top_level.txt
ipyreactplayer-0.0.2.dist-info/RECORD
